{
  "code": "0000",
  "message": "成功",
  "data": {
    "2073": {
      "numFound": 4,
      "item": [
        {
          "school_id": "161",
          "province_id": "43",
          "type": "2073",
          "batch": "14",
          "zslx": "0",
          "xclevel": "0",
          "max": "-",
          "min_section": "40363",
          "min": "552",
          "average": "-",
          "filing": "552",
          "special_group": "104931",
          "first_km": "70000",
          "num": "-",
          "local_province_name": "湖南",
          "local_type_name": "物理类",
          "local_batch_id": "14",
          "local_batch_name": "本科批",
          "zslx_name": "普通类",
          "xclevel_name": "-",
          "zslx_rank": 200,
          "sg_fxk": "70000",
          "sg_sxk": "70001",
          "sg_type": "80003",
          "sg_name": "（105）",
          "sg_info": "首选物理，再选化学",
          "proscore": "415",
          "year": "2023",
          "diff": 137
        },
        {
          "school_id": "161",
          "province_id": "43",
          "type": "2073",
          "batch": "14",
          "zslx": "0",
          "xclevel": "0",
          "max": "-",
          "min_section": "43010",
          "min": "548",
          "average": "-",
          "filing": "548",
          "special_group": "104933",
          "first_km": "70000",
          "num": "-",
          "local_province_name": "湖南",
          "local_type_name": "物理类",
          "local_batch_id": "14",
          "local_batch_name": "本科批",
          "zslx_name": "普通类",
          "xclevel_name": "-",
          "zslx_rank": 200,
          "sg_fxk": "70000",
          "sg_sxk": "70008",
          "sg_type": "80001",
          "sg_name": "（103）",
          "sg_info": "首选物理，再选不限",
          "proscore": "415",
          "year": "2023",
          "diff": 133
        },
        {
          "school_id": "161",
          "province_id": "43",
          "type": "2073",
          "batch": "14",
          "zslx": "0",
          "xclevel": "0",
          "max": "-",
          "min_section": "45798",
          "min": "544",
          "average": "-",
          "filing": "544",
          "special_group": "104932",
          "first_km": "70000",
          "num": "-",
          "local_province_name": "湖南",
          "local_type_name": "物理类",
          "local_batch_id": "14",
          "local_batch_name": "本科批",
          "zslx_name": "普通类",
          "xclevel_name": "-",
          "zslx_rank": 200,
          "sg_fxk": "70000",
          "sg_sxk": "70001",
          "sg_type": "80003",
          "sg_name": "（104）",
          "sg_info": "首选物理，再选化学",
          "proscore": "415",
          "year": "2023",
          "diff": 129
        },
        {
          "school_id": "161",
          "province_id": "43",
          "type": "2073",
          "batch": "14",
          "zslx": "0",
          "xclevel": "0",
          "max": "-",
          "min_section": "50112",
          "min": "538",
          "average": "-",
          "filing": "538",
          "special_group": "104930",
          "first_km": "70000",
          "num": "-",
          "local_province_name": "湖南",
          "local_type_name": "物理类",
          "local_batch_id": "14",
          "local_batch_name": "本科批",
          "zslx_name": "普通类",
          "xclevel_name": "-",
          "zslx_rank": 200,
          "sg_fxk": "70000",
          "sg_sxk": "70001,70002",
          "sg_type": "80002",
          "sg_name": "（106）",
          "sg_info": "首选物理，再选化学/生物(2选1)",
          "proscore": "415",
          "year": "2023",
          "diff": 123
        }
      ]
    },
    "2074": {
      "numFound": 1,
      "item": [
        {
          "school_id": "161",
          "province_id": "43",
          "type": "2074",
          "batch": "14",
          "zslx": "0",
          "xclevel": "0",
          "max": "-",
          "min_section": "14340",
          "min": "519",
          "average": "-",
          "filing": "519",
          "special_group": "104934",
          "first_km": "70004",
          "num": "-",
          "local_province_name": "湖南",
          "local_type_name": "历史类",
          "local_batch_id": "14",
          "local_batch_name": "本科批",
          "zslx_name": "普通类",
          "xclevel_name": "-",
          "zslx_rank": 200,
          "sg_fxk": "70004",
          "sg_sxk": "70008",
          "sg_type": "80001",
          "sg_name": "（101）",
          "sg_info": "首选历史，再选不限",
          "proscore": "428",
          "year": "2023",
          "diff": 91
        }
      ]
    }
  },
  "md5": "b32d0e07584ed15d59fc15d791f0e590",
  "time": "2025-06-13 17:03:00"
}