{
  "code": "0000",
  "message": "成功",
  "data": {
    "2073": {
      "numFound": 1,
      "item": [
        {
          "school_id": "725",
          "province_id": "43",
          "type": "2073",
          "batch": "10",
          "zslx": "0",
          "xclevel": "0",
          "max": "-",
          "min_section": "184636",
          "min": "389",
          "average": "-",
          "filing": "389",
          "special_group": "67401",
          "first_km": "70000",
          "num": "-",
          "local_province_name": "湖南",
          "local_type_name": "物理类",
          "local_batch_id": "10",
          "local_batch_name": "专科批",
          "zslx_name": "普通类",
          "xclevel_name": "-",
          "zslx_rank": 200,
          "sg_fxk": "70000",
          "sg_sxk": "70008",
          "sg_type": "80001",
          "sg_name": "（002）",
          "sg_info": "首选物理，再选不限",
          "proscore": "200",
          "year": "2022",
          "diff": 189
        }
      ]
    },
    "2074": {
      "numFound": 1,
      "item": [
        {
          "school_id": "725",
          "province_id": "43",
          "type": "2074",
          "batch": "10",
          "zslx": "0",
          "xclevel": "0",
          "max": "-",
          "min_section": "69706",
          "min": "435",
          "average": "-",
          "filing": "435",
          "special_group": "63222",
          "first_km": "70004",
          "num": "-",
          "local_province_name": "湖南",
          "local_type_name": "历史类",
          "local_batch_id": "10",
          "local_batch_name": "专科批",
          "zslx_name": "普通类",
          "xclevel_name": "-",
          "zslx_rank": 200,
          "sg_fxk": "70004",
          "sg_sxk": "70008",
          "sg_type": "80001",
          "sg_name": "（001）",
          "sg_info": "首选历史，再选不限",
          "proscore": "200",
          "year": "2022",
          "diff": 235
        }
      ]
    }
  },
  "md5": "3d49c2931d6ba800671e071f77977ef0",
  "time": "2025-06-11 18:30:15"
}