{
  "code": "0000",
  "message": "成功",
  "data": {
    "2073": {
      "numFound": 6,
      "item": [
        {
          "school_id": "661",
          "province_id": "43",
          "type": "2073",
          "batch": "14",
          "zslx": "0",
          "xclevel": "0",
          "max": "-",
          "min_section": "2633",
          "min": "647",
          "average": "-",
          "filing": "647",
          "special_group": "194157",
          "first_km": "70000",
          "num": "-",
          "local_province_name": "湖南",
          "local_type_name": "物理类",
          "local_batch_id": "14",
          "local_batch_name": "本科批",
          "zslx_name": "普通类",
          "xclevel_name": "-",
          "zslx_rank": 200,
          "sg_fxk": "70000",
          "sg_sxk": "70001",
          "sg_type": "80003",
          "sg_name": "（102）",
          "sg_info": "首选物理，再选化学",
          "proscore": "422",
          "year": "2024",
          "diff": 225
        },
        {
          "school_id": "661",
          "province_id": "43",
          "type": "2073",
          "batch": "14",
          "zslx": "610",
          "xclevel": "0",
          "max": "-",
          "min_section": "2761",
          "min": "646",
          "average": "-",
          "filing": "646",
          "special_group": "195386",
          "first_km": "70000",
          "num": "-",
          "local_province_name": "湖南",
          "local_type_name": "物理类",
          "local_batch_id": "14",
          "local_batch_name": "本科批",
          "zslx_name": "沙河校区",
          "xclevel_name": "-",
          "zslx_rank": 100,
          "sg_fxk": "70000",
          "sg_sxk": "70001",
          "sg_type": "80003",
          "sg_name": "（101）",
          "sg_info": "首选物理，再选化学",
          "proscore": "422",
          "year": "2024",
          "diff": 224
        },
        {
          "school_id": "661",
          "province_id": "43",
          "type": "2073",
          "batch": "14",
          "zslx": "555",
          "xclevel": "0",
          "max": "-",
          "min_section": "3766",
          "min": "639",
          "average": "-",
          "filing": "639",
          "special_group": "190239",
          "first_km": "70000",
          "num": "-",
          "local_province_name": "湖南",
          "local_type_name": "物理类",
          "local_batch_id": "14",
          "local_batch_name": "本科批",
          "zslx_name": "国家专项计划",
          "xclevel_name": "-",
          "zslx_rank": 100,
          "sg_fxk": "70000",
          "sg_sxk": "70001",
          "sg_type": "80003",
          "sg_name": "（303）",
          "sg_info": "首选物理，再选化学",
          "proscore": "422",
          "year": "2024",
          "diff": 217
        },
        {
          "school_id": "661",
          "province_id": "43",
          "type": "2073",
          "batch": "14",
          "zslx": "3588",
          "xclevel": "0",
          "max": "-",
          "min_section": "5460",
          "min": "630",
          "average": "-",
          "filing": "630",
          "special_group": "190640",
          "first_km": "70000",
          "num": "-",
          "local_province_name": "湖南",
          "local_type_name": "物理类",
          "local_batch_id": "14",
          "local_batch_name": "本科批",
          "zslx_name": "沙河校区中外合作办学或国际项目",
          "xclevel_name": "-",
          "zslx_rank": 100,
          "sg_fxk": "70000",
          "sg_sxk": "70001",
          "sg_type": "80003",
          "sg_name": "（203）",
          "sg_info": "首选物理，再选化学",
          "proscore": "422",
          "year": "2024",
          "diff": 208
        },
        {
          "school_id": "661",
          "province_id": "43",
          "type": "2073",
          "batch": "14",
          "zslx": "3588",
          "xclevel": "0",
          "max": "-",
          "min_section": "6853",
          "min": "624",
          "average": "-",
          "filing": "624",
          "special_group": "190592",
          "first_km": "70000",
          "num": "-",
          "local_province_name": "湖南",
          "local_type_name": "物理类",
          "local_batch_id": "14",
          "local_batch_name": "本科批",
          "zslx_name": "沙河校区中外合作办学或国际项目",
          "xclevel_name": "-",
          "zslx_rank": 100,
          "sg_fxk": "70000",
          "sg_sxk": "70001",
          "sg_type": "80003",
          "sg_name": "（204）",
          "sg_info": "首选物理，再选化学",
          "proscore": "422",
          "year": "2024",
          "diff": 202
        },
        {
          "school_id": "661",
          "province_id": "43",
          "type": "2073",
          "batch": "14",
          "zslx": "610",
          "xclevel": "0",
          "max": "-",
          "min_section": "7093",
          "min": "623",
          "average": "-",
          "filing": "623",
          "special_group": "194156",
          "first_km": "70000",
          "num": "-",
          "local_province_name": "湖南",
          "local_type_name": "物理类",
          "local_batch_id": "14",
          "local_batch_name": "本科批",
          "zslx_name": "沙河校区",
          "xclevel_name": "-",
          "zslx_rank": 100,
          "sg_fxk": "70000",
          "sg_sxk": "70001",
          "sg_type": "80003",
          "sg_name": "（102）",
          "sg_info": "首选物理，再选化学",
          "proscore": "422",
          "year": "2024",
          "diff": 201
        }
      ]
    },
    "2074": {
      "numFound": 1,
      "item": [
        {
          "school_id": "661",
          "province_id": "43",
          "type": "2074",
          "batch": "14",
          "zslx": "0",
          "xclevel": "0",
          "max": "-",
          "min_section": "1905",
          "min": "601",
          "average": "-",
          "filing": "601",
          "special_group": "195387",
          "first_km": "70004",
          "num": "-",
          "local_province_name": "湖南",
          "local_type_name": "历史类",
          "local_batch_id": "14",
          "local_batch_name": "本科批",
          "zslx_name": "普通类",
          "xclevel_name": "-",
          "zslx_rank": 200,
          "sg_fxk": "70004",
          "sg_sxk": "70008",
          "sg_type": "80001",
          "sg_name": "（101）",
          "sg_info": "首选历史，再选不限",
          "proscore": "438",
          "year": "2024",
          "diff": 163
        }
      ]
    }
  },
  "md5": "e6251edbba9bae502a073e6ff65cb104",
  "time": "2025-06-11 18:26:55"
}